requests_tracker/__init__.py
requests_tracker/apps.py
requests_tracker/base_collector.py
requests_tracker/headers/__init__.py
requests_tracker/headers/header_collector.py
requests_tracker/main_request_collector.py
requests_tracker/middleware.py
requests_tracker/settings.py
requests_tracker/sql/__init__.py
requests_tracker/sql/dataclasses.py
requests_tracker/sql/sql_collector.py
requests_tracker/sql/sql_hook.py
requests_tracker/sql/sql_parser.py
requests_tracker/sql/sql_tracker.py
requests_tracker/sql/utils.py
requests_tracker/stack_trace.py
requests_tracker/static/requests_tracker/css/base.css
requests_tracker/static/requests_tracker/css/base.css.map
requests_tracker/static/requests_tracker/css/bulma-prefers-dark.css
requests_tracker/static/requests_tracker/css/index.css
requests_tracker/static/requests_tracker/css/index.css.map
requests_tracker/static/requests_tracker/css/request-details.css
requests_tracker/static/requests_tracker/css/request-details.css.map
requests_tracker/static/requests_tracker/css/variabels.css
requests_tracker/static/requests_tracker/css/variabels.css.map
requests_tracker/static/requests_tracker/sass/base.sass
requests_tracker/static/requests_tracker/sass/index.sass
requests_tracker/static/requests_tracker/sass/request-details.sass
requests_tracker/static/requests_tracker/sass/variabels.sass
requests_tracker/templates/base.html
requests_tracker/templates/components/table.html
requests_tracker/templates/django_settings.html
requests_tracker/templates/index.html
requests_tracker/templates/partials/loading_indicator_partial.html
requests_tracker/templates/partials/request_details_headers_partial.html
requests_tracker/templates/partials/request_details_partial.html
requests_tracker/templates/partials/request_details_sql_partial.html
requests_tracker/templates/partials/request_list_item.html
requests_tracker/templates/partials/request_list_only_partial.html
requests_tracker/templates/partials/request_list_partial.html
requests_tracker-0.3.3.dist-info/METADATA
requests_tracker-0.3.3.dist-info/WHEEL
requests_tracker-0.3.3.dist-info/RECORD
