Metadata-Version: 2.1
Name: requests-tracker
Version: 0.3.3
Summary: The Django Requests Tracker is designed for local Django development, particularly for Rest API development. It provides various debugging information, such as SQL queries, headers, and status codes.
Home-page: https://github.com/bensi94/Django-Requests-Tracker
License: MIT
Keywords: django,python,sql,middlware,api,rest,debug,htmx,django-rest-framework,django-ninja,requests-tracker,django-requests-tracker,development
Author: Benedikt Óskarsson
Author-email: bensi94@hotmail.com
Requires-Python: >=3.8,<4.0
Classifier: Environment :: Web Environment
Classifier: Framework :: Django
Classifier: Intended Audience :: Developers
Classifier: Intended Audience :: Information Technology
Classifier: License :: OSI Approved :: MIT License
Classifier: Operating System :: OS Independent
Classifier: Programming Language :: Python
Classifier: Programming Language :: Python :: 3
Classifier: Programming Language :: Python :: 3.8
Classifier: Programming Language :: Python :: 3.9
Classifier: Programming Language :: Python :: 3.10
Classifier: Programming Language :: Python :: 3.11
Classifier: Programming Language :: Python :: 3 :: Only
Classifier: Programming Language :: Python :: 3.12
Classifier: Topic :: Internet :: WWW/HTTP
Classifier: Topic :: Internet :: WWW/HTTP :: HTTP Servers
Classifier: Topic :: Software Development
Classifier: Topic :: Software Development :: Libraries
Classifier: Topic :: Software Development :: Libraries :: Python Modules
Classifier: Typing :: Typed
Requires-Dist: django (>=3.2)
Requires-Dist: sqlparse (>=0.4.3)
Project-URL: Documentation, https://github.com/bensi94/Django-Requests-Tracker/blob/main/README.md
Project-URL: Repository, https://github.com/bensi94/Django-Requests-Tracker
